AuroraLobbybot/__init__.py
AuroraLobbybot/keep_alive.py
AuroraLobbybot/lb.py
AuroraLobbybot-6.0.0.dist-info/LICENSE
AuroraLobbybot-6.0.0.dist-info/METADATA
AuroraLobbybot-6.0.0.dist-info/WHEEL
AuroraLobbybot-6.0.0.dist-info/top_level.txt
AuroraLobbybot-6.0.0.dist-info/RECORD
