Metadata-Version: 2.1
Name: AuroraLobbybot
Version: 6.0.0
Summary: Python package to create FN Lobbybots
Author: Zockerwolf76
Author-email: 
Classifier: Programming Language :: Python :: 3
Requires-Python: >=3.6
License-File: LICENSE
